xj_dictionary/__init__.py
xj_dictionary/admin.py
xj_dictionary/apps.py
xj_dictionary/forms.py
xj_dictionary/middleware.py
xj_dictionary/models.py
xj_dictionary/urls.py
xj_dictionary/apis/__init__.py
xj_dictionary/apis/dictionary_configure.py
xj_dictionary/services/__init__.py
xj_dictionary/services/config_service.py
xj_dictionary/utils/__init__.py
xj_dictionary/utils/custom_response.py
xj_dictionary/utils/custom_tool.py
xj_dictionary/utils/model_handle.py
xj_dictionary-1.1.0.dist-info/METADATA
xj_dictionary-1.1.0.dist-info/WHEEL
xj_dictionary-1.1.0.dist-info/top_level.txt
xj_dictionary-1.1.0.dist-info/RECORD
