Metadata-Version: 2.1
Name: xj-dictionary
Version: 1.1.0
Summary: 配置模块
Home-page: UNKNOWN
License: apache 3.0
Platform: UNKNOWN
